{
  "run_time": "2026-06-01T14:04:00+08:00",
  "quotes_snapshot": "行情快照_2026-06-01_1404.json",
  "report": "数据服务摘要_2026-06-01_1404.md",
  "tracker_updated": false,
  "tracker_note": "无新增严重舆情，美伊冲突severe已在13:37更新",
  "data_files": [
    "mx_data_科创50、半导体板块、人工智能板块、计算机行业、通信设备今日最新涨跌幅和主力资金流向 (14:04 -3.85%/-2.93%/+3.3%/-1.44%)",
    "mx_data_上证指数今日最新收盘价和涨跌幅 (14:05 4062.73 -0.14%)",
    "mx_data_北向资金今日净买入 (5/29 4734亿)",
    "mx_search_财联社_2026年6月1日_A股市场要闻_重大新闻_行业动态_科技板块_午后行情",
    "mx_search_今日A股午后行情_计算机_AI应用_煤炭_半导体_实时快讯",
    "mx_search_美伊冲突最新进展_2026年6月1日_伊朗_霍尔木兹_原油"
  ],
  "severe_alerts": []
}
