{
  "snapshot_time": "2026-06-01T15:06:00+08:00",
  "market_date": "2026-06-01",
  "indexes": {
    "上证指数": {"code": "000001.SH", "change_pct": -0.27, "volume": "1.32万亿元"},
    "深证成指": {"code": "399001.SZ", "change_pct": -1.51, "volume": "1.558万亿元"},
    "创业板指": {"code": "399006.SZ", "change_pct": -2.15, "volume": "7346亿元"},
    "科创50": {"code": "000688.SH", "change_pct": -5.00, "volume": "1499亿元"},
    "中证全指": {"code": "000985.CSI", "change_pct": -0.0075, "volume": "2.803万亿元"}
  },
  "tech_sectors": {
    "计算机": {"change_pct": 3.0, "volume": "1608亿元", "5d_change": -5.69, "up_count": 306, "down_count": 52, "support": 8297.67, "resistance": 9540.59},
    "电子": {"change_pct": -1.67, "volume": "8666亿元", "5d_change": -7.28, "up_count": 172, "down_count": 332, "support": 12178.32, "resistance": 14718.74}
  },
  "market_breadth": {
    "上涨家数": 3459,
    "下跌家数": 1556,
    "平盘家数": 41,
    "上涨占比": "68.4%"
  },
  "capital_flow": {
    "主力净流入板块": ["计算机", "文化传媒", "煤炭采选"],
    "主力净流出板块": ["电子", "半导体", "机械设备"],
    "电子净流出": "268.79亿元",
    "个股净买第一": {"name": "风华高科", "amount": "8.11亿元"},
    "个股净卖第一": {"name": "东山精密", "amount": "34.95亿元"}
  },
  "key_events": [
    "科创50暴跌5%，科技股调整延续；基金风格漂移监管重拳落地，近4000亿资金被迫调仓",
    "英伟达GTC Taipei发布Vera CPU，AI应用/软件板块走强，计算机涨3%",
    "宇树科技科创板IPO今日上会；长鑫科技IPO已获通过",
    "伊朗革命卫队确认美军袭击霍尔木兹省通信塔，革命卫队打击美军基地回应",
    "《国务院关于对外投资的规定》公布，7月1日起施行",
    "5月制造业PMI 50.0%临界点，较上月降0.3个百分点"
  ],
  "northbound": {
    "status": "API调用次数耗尽，数据暂缺"
  }
}
