{
  "snapshot_time": "2026-05-30 21:03 (Asia/Shanghai)",
  "market_status": "WEEKEND (Saturday, no trading)",
  "last_trading_day": "2026-05-29 (Friday)",
  "next_trading_day": "2026-06-01 (Monday)",
  "note": "周六21:03休市，上一小时(20:20→21:03)无新增行情/舆情变化。A股已收市1天+。",
  "indices": {
    "上证指数": { "close": 4068.57, "change_pct": -0.73 },
    "深证成指": { "close": 15575.13, "change_pct": -1.81 },
    "创业板指": { "close": 4037.95, "change_pct": -2.11 },
    "沪深300": { "close": 4892.12, "change_pct": -0.45 },
    "科创50": { "close": 1751.32, "change_pct": -5.04 }
  },
  "tech_sector_spotlight": {
    "半导体_BK1036": {
      "latest_date": "2026-05-29",
      "change_pct_total_weighted": -5.622,
      "change_pct_avg": -6.398,
      "turnover": "4830亿元",
      "volume": "60.43亿股",
      "advance": 11,
      "decline": 164,
      "flat": 2,
      "detail_5d_pct": ["周五-5.62%","周四+2.61%","周三-2.11%","周二-1.36%","周一+7.66%"]
    },
    "人工智能_BK0800": {
      "latest_date": "2026-05-29",
      "change_pct": -3.247,
      "turnover": "5398亿元",
      "advance_decline": "113涨/582跌/7平"
    }
  },
  "market_breadth": {
    "全市场成交(5/29)": "约3.34万亿",
    "近5日量能趋势": "3.39/3.31/3.30/3.27/3.34万亿",
    "北向资金(5/29)": "净买入56.69亿元（逆势加仓）",
    "北向资金(5/28)": "净买入249亿元（单日大额流入）",
    "融资余额(5/28)": "约2.94万亿，逼3万亿",
    "融资净买入(本周)": "423亿，连续第8周加仓"
  },
  "overseas_close_20260529": {
    "道指": "51032.46(+0.72%)",
    "标普500": "7580.06(+0.22%)",
    "纳指": "26972.62(+0.20%)",
    "WTI原油": "87.76(-1.28%)",
    "布伦特原油": "91.66(-1.26%)",
    "黄金": "4569.90(+0.83%)",
    "10Y美债": "4.4355%"
  },
  "weekend_updates": {
    "time_span": "2026-05-30 20:20 → 21:03",
    "change_detected": false,
    "reason": "周六晚休市，20:20→21:03无新增行情变化或重大突发舆情"
  }
}
